casstest/__init__.py
casstest/casstest.py
casstest/stresstest.py
casstest-0.7.0.dist-info/DESCRIPTION.rst
casstest-0.7.0.dist-info/entry_points.txt
casstest-0.7.0.dist-info/METADATA
casstest-0.7.0.dist-info/metadata.json
casstest-0.7.0.dist-info/RECORD
casstest-0.7.0.dist-info/top_level.txt
casstest-0.7.0.dist-info/WHEEL
