Metadata-Version: 2.0
Name: casstest
Version: 0.7.0
Summary: Just a quick dockerfile test for my entertainment
Home-page: https://github.com/goller/casstest
Author: Chris Goller
Author-email: goller@gmail.com
License: BSD
Keywords: casstest
Platform: UNKNOWN
Classifier: Development Status :: 2 - Pre-Alpha
Classifier: Intended Audience :: Developers
Classifier: License :: OSI Approved :: BSD License
Classifier: Natural Language :: English
Classifier: Programming Language :: Python :: 2
Classifier: Programming Language :: Python :: 2.6
Classifier: Programming Language :: Python :: 2.7
Classifier: Programming Language :: Python :: 3
Classifier: Programming Language :: Python :: 3.3
Classifier: Programming Language :: Python :: 3.4
Requires-Dist: blist (==1.3.6)
Requires-Dist: cassandra-driver (==2.1.3)
Requires-Dist: docopt (==0.6.2)
